pylintseq/__init__.py
pylintseq/generate.py
pylintseq/utils.py
pylintseq-0.0.2.dist-info/LICENSE
pylintseq-0.0.2.dist-info/METADATA
pylintseq-0.0.2.dist-info/WHEEL
pylintseq-0.0.2.dist-info/entry_points.txt
pylintseq-0.0.2.dist-info/top_level.txt
pylintseq-0.0.2.dist-info/RECORD
