Metadata-Version: 2.1
Name: pylintseq
Version: 0.0.2
Summary: LintSeq with PyLint-Guided Sampling
Author-email: Ulyana Piterbarg <up2021@nyu.edu>
Project-URL: Homepage, https://lintseq.github.io
Project-URL: Repository, https://github.com/upiterbarg/pylintseq.git
Classifier: Programming Language :: Python :: 3
Classifier: License :: OSI Approved :: MIT License
Classifier: Operating System :: OS Independent
Requires-Python: >=3.9
License-File: LICENSE
Requires-Dist: jsonlines
Requires-Dist: pylint
Requires-Dist: numpy
Requires-Dist: pandas
Requires-Dist: tqdm
Requires-Dist: joblib
Requires-Dist: psutil
